NetworkManager.py
python_networkmanager-2.2.dist-info/COPYING
python_networkmanager-2.2.dist-info/METADATA
python_networkmanager-2.2.dist-info/WHEEL
python_networkmanager-2.2.dist-info/top_level.txt
python_networkmanager-2.2.dist-info/RECORD
